greedybfs/__init__.py
greedybfs/graph.py
greedybfs/greedybfs.py
greedybfs/priorityQueue.py
greedybfs-0.1.4.dist-info/AUTHORS.rst
greedybfs-0.1.4.dist-info/LICENSE
greedybfs-0.1.4.dist-info/METADATA
greedybfs-0.1.4.dist-info/WHEEL
greedybfs-0.1.4.dist-info/top_level.txt
greedybfs-0.1.4.dist-info/RECORD
