Metadata-Version: 2.1
Name: greedybfs
Version: 0.1.4
Summary: Implementation of Greedy BFS algorithm
Home-page: https://github.com/chinmayshah99/greedybfs
Author: Chinmay Shah
Author-email: chinmayshah3899@gmail.com
License: MIT license
Keywords: greedybfs
Platform: UNKNOWN
Classifier: Development Status :: 2 - Pre-Alpha
Classifier: Intended Audience :: Developers
Classifier: License :: OSI Approved :: MIT License
Classifier: Natural Language :: English
Classifier: Programming Language :: Python :: 3
Classifier: Programming Language :: Python :: 3.5
Classifier: Programming Language :: Python :: 3.6
Classifier: Programming Language :: Python :: 3.7
Requires-Python: >=3.5
